{
  "project_info": {
    "project_number": "483796877712",
    "project_id": "mobile-app-d8647",
    "storage_bucket": "mobile-app-d8647.firebasestorage.app"
  },
  "client": [
    {
      "client_info": {
        "mobilesdk_app_id": "1:483796877712:android:e2c2c20ceaf93b3c03f315",
        "android_client_info": {
          "package_name": "com.example.mobileapp"
        }
      },
      "oauth_client": [],
      "api_key": [
        {
          "current_key": "AIzaSyBSIEq--9CBANCtmKjcFqVZ8PNUamw7gmU"
        }
      ],
      "services": {
        "appinvite_service": {
          "other_platform_oauth_client": []
        }
      }
    }
  ],
  "configuration_version": "1"
}